airtable_fdw/__init__.py
airtable_fdw/test_airtablefdw.py
airtable_fdw/utils.py
airtable_fdw-0.3.4.dist-info/WHEEL
airtable_fdw-0.3.4.dist-info/METADATA
airtable_fdw-0.3.4.dist-info/RECORD
