Metadata-Version: 2.1
Name: airtable-fdw
Version: 0.3.4
Summary: Airtable Multicorn FDW for Postgres
License: MIT
Author: Sebastian Szymbor
Author-email: thesebas@users.noreply.github.com
Requires-Python: >=3.7,<4.0
Classifier: Development Status :: 3 - Alpha
Classifier: License :: OSI Approved :: MIT License
Classifier: Programming Language :: Python :: 3
Classifier: Programming Language :: Python :: 3.10
Classifier: Programming Language :: Python :: 3.7
Classifier: Programming Language :: Python :: 3.8
Classifier: Programming Language :: Python :: 3.9
Requires-Dist: airtable-python-wrapper (==0.15.3)
